pyEYE2/__init__.py
pyEYE2/pyEYE2_cpp.cpython-39-x86_64-linux-gnu.so
pyeye2-0.0.2.dist-info/METADATA
pyeye2-0.0.2.dist-info/WHEEL
pyeye2-0.0.2.dist-info/top_level.txt
pyeye2-0.0.2.dist-info/RECORD
pyeye2-0.0.2.dist-info/licenses/LICENSE
