Metadata-Version: 2.4
Name: pyEYE2
Version: 0.0.2
Summary: Python bindings to connect and operate the EYE2 device across Windows, Linux, and macOS
Author-email: gaopeng <gaopeng@jcdz.cc>
Classifier: Programming Language :: Python :: 3
Classifier: Programming Language :: Python :: 3.9
Classifier: Programming Language :: Python :: 3.10
Classifier: Programming Language :: Python :: 3.11
Classifier: Programming Language :: Python :: 3.12
Classifier: License :: OSI Approved :: MIT License
Classifier: Operating System :: Microsoft :: Windows
Classifier: Operating System :: POSIX :: Linux
Classifier: Operating System :: MacOS
Requires-Python: <3.13,>=3.9
License-File: LICENSE
Dynamic: license-file
